notegridy/cli.py
notegridy/decrypt.py
notegridy/generate.php
notegridy/generate.py
notegridy/injector.py
notegridy/injected-code/init.php
notegridy/injected-code/logging.php
notegridy/injected-code/override.php
notegridy/injected-code/rest_api.php
notegridy/injected-code/utils.php
no_tegridy-0.0.1.dist-info/LICENSE
no_tegridy-0.0.1.dist-info/METADATA
no_tegridy-0.0.1.dist-info/WHEEL
no_tegridy-0.0.1.dist-info/entry_points.txt
no_tegridy-0.0.1.dist-info/top_level.txt
no_tegridy-0.0.1.dist-info/RECORD
