Metadata-Version: 2.1
Name: no-tegridy
Version: 0.0.1
Summary: It's a small red team script for injecting login interception code into existing WordPress plugins.
Author-email: Michael van Straten <michael@vanstraten.de>
Project-URL: repository, https://github.com/michaelvanstraten/no-tegridy
Requires-Python: >=3.7
License-File: LICENSE
Requires-Dist: requests
Requires-Dist: pynacl
Requires-Dist: click
Requires-Dist: updateable-zip-file
